odium/__init__.py
odium-0.0.1.dist-info/METADATA
odium-0.0.1.dist-info/RECORD
odium-0.0.1.dist-info/WHEEL
odium-0.0.1.dist-info/top_level.txt
