Metadata-Version: 2.1
Name: odium
Version: 0.0.1
Summary: remote execution framework
Home-page: https://github.com/seanharrison/odium
Author: Sean Harrison
Author-email: sah@bookgenesis.com
License: MPL 2.0
Platform: UNKNOWN
Classifier: Development Status :: 1 - Planning
Classifier: Intended Audience :: Developers
Classifier: License :: OSI Approved :: Mozilla Public License 2.0 (MPL 2.0)
Classifier: Programming Language :: Python :: 3
Provides-Extra: dev
Provides-Extra: test
Provides-Extra: dev
Provides-Extra: test
